EOSgenerators/Compose_eos.py
EOSgenerators/MITbag_EOS.py
EOSgenerators/Polytrope_EOS.py
EOSgenerators/RMF_DDH.py
EOSgenerators/RMF_EOS.py
EOSgenerators/SpeedofSound_EOS.py
EOSgenerators/Strangeon_EOS.py
EOSgenerators/__init__.py
EOSgenerators/crust_EOS.py
EOSgenerators/download_compose.py
EOSgenerators/fastRMF_EoS.py
EOSgenerators/parameterized_EOS.py
InferenceWorkflow/BayesianSampler.py
InferenceWorkflow/DDH_Likelihood.py
InferenceWorkflow/Likelihood.py
InferenceWorkflow/__init__.py
InferenceWorkflow/pQCD.py
InferenceWorkflow/prior.py
TOVsolver/EoS_import.py
TOVsolver/__init__.py
TOVsolver/constant.py
TOVsolver/main.py
TOVsolver/maximum_central_density.py
TOVsolver/solver_code.py
TOVsolver/speed_of_sound.py
TOVsolver/tests_script.py
TOVsolver/unit.py
compactobject_tov-2.1.dist-info/licenses/LICENSE
compactobject_tov-2.1.dist-info/licenses/LICENSE_short
postprocessing/Cornerplot.py
postprocessing/__init__.py
postprocessing/corner_plot_example.py
compactobject_tov-2.1.dist-info/METADATA
compactobject_tov-2.1.dist-info/WHEEL
compactobject_tov-2.1.dist-info/top_level.txt
compactobject_tov-2.1.dist-info/RECORD
