Metadata-Version: 2.4
Name: CompactObject_TOV
Version: 2.1
Summary: A small example package
Author-email: Chun Huang <author@example.com>
Project-URL: Homepage, https://github.com/ChunHuangPhy/CompactOject
Project-URL: Issues, https://github.com/ChunHuangPhy/CompactOject/issues
Classifier: Programming Language :: Python :: 3
Classifier: License :: OSI Approved :: MIT License
Classifier: Operating System :: OS Independent
Requires-Python: >=3.8
License-File: LICENSE
License-File: LICENSE_short
Requires-Dist: contourpy
Requires-Dist: corner
Requires-Dist: cycler
Requires-Dist: fonttools
Requires-Dist: kiwisolver
Requires-Dist: matplotlib
Requires-Dist: numpy
Requires-Dist: packaging
Requires-Dist: pillow
Requires-Dist: pyparsing
Requires-Dist: python-dateutil
Requires-Dist: six
Requires-Dist: scipy
Dynamic: license-file
